<?xml version='1.0'?>
<list>
    <option name="org.ton.tolk.MUT_PARAMETER">
        <value>
            <option name="FOREGROUND" value="1C5DFE" />
            <option name="EFFECT_COLOR" value="81A1ED"/>
            <option name="EFFECT_TYPE" value="1" />
        </value>
    </option>
    <option name="org.ton.tolk.MUT_SELF_PARAMETER">
        <value>
            <option name="FOREGROUND" value="0033B3" />
            <option name="EFFECT_COLOR" value="7595D3"/>
            <option name="EFFECT_TYPE" value="1" />
        </value>
    </option>
    <option name="org.ton.tolk.STRUCT">
        <value>
            <option name="FOREGROUND" value="a04908" />
        </value>
    </option>
    <option name="org.ton.tolk.EMPTY_STRUCT">
        <value>
            <option name="FOREGROUND" value="0E7FC5" />
            <option name="FONT_TYPE" value="2" />
        </value>
    </option>
    <option name="org.ton.tolk.TYPE_ALIAS">
        <value>
            <option name="FOREGROUND" value="a04908" />
            <option name="FONT_TYPE" value="2" />
        </value>
    </option>
</list>
